_sxtwl.cpython-314-darwin.so
sxtwl.py
sxtwl_modern-1.1.2.dist-info/METADATA
sxtwl_modern-1.1.2.dist-info/WHEEL
sxtwl_modern-1.1.2.dist-info/top_level.txt
sxtwl_modern-1.1.2.dist-info/RECORD
