Metadata-Version: 2.4
Name: sxtwl-modern
Version: 1.1.2
Summary: Sxtwl_cpp wrapper for Python - Chinese Lunar Calendar Library
Home-page: https://github.com/SIC98/sxtwl
Author: yuangu
Author-email: yuangu <lifulinghan@aol.com>
License: BSD
Project-URL: Homepage, https://github.com/SIC98/sxtwl
Project-URL: Repository, https://github.com/SIC98/sxtwl
Project-URL: Bug Tracker, https://github.com/SIC98/sxtwl/issues
Keywords: lunar,calendar,chinese,astronomy
Classifier: Development Status :: 4 - Beta
Classifier: Intended Audience :: Developers
Classifier: License :: OSI Approved :: BSD License
Classifier: Operating System :: MacOS
Classifier: Operating System :: POSIX :: Linux
Classifier: Operating System :: Microsoft :: Windows
Classifier: Programming Language :: Python :: 3
Classifier: Programming Language :: Python :: 3.8
Classifier: Programming Language :: Python :: 3.9
Classifier: Programming Language :: Python :: 3.10
Classifier: Programming Language :: Python :: 3.11
Classifier: Programming Language :: Python :: 3.12
Classifier: Programming Language :: Python :: 3.13
Classifier: Programming Language :: C++
Classifier: Topic :: Software Development :: Libraries :: Python Modules
Requires-Python: >=3.8
Dynamic: author
Dynamic: home-page
Dynamic: requires-python
